ts3ekkosingle/__init__.py
ts3ekkosingle/argparser.py
ts3ekkosingle/bot.py
ts3ekkosingle/command.py
ts3ekkosingle/entrypoint.py
ts3ekkosingle/errors.py
ts3ekkosingle/event_type.py
ts3ekkosingle/models.py
ts3ekkosingle/permission.py
ts3ekkosingle/ts3ekko.py
ts3ekkosingle/ts3identity.py
ts3ekkosingle/cogs/__init__.py
ts3ekkosingle/cogs/fun.py
ts3ekkosingle/cogs/media.py
ts3ekkosingle-0.0.21.dist-info/METADATA
ts3ekkosingle-0.0.21.dist-info/WHEEL
ts3ekkosingle-0.0.21.dist-info/entry_points.txt
ts3ekkosingle-0.0.21.dist-info/top_level.txt
ts3ekkosingle-0.0.21.dist-info/RECORD
