Metadata-Version: 2.1
Name: ts3ekkosingle
Version: 0.0.21
Summary: ts3ekkosingle
Home-page: https://gitlab.com/networkjanitor/ts3ekkosingle
Author: Xyoz Netsphere
Author-email: nanoowl@xyooz.net
License: MIT
Platform: UNKNOWN
Classifier: Development Status :: 3 - Alpha
Classifier: License :: OSI Approved :: MIT License
Classifier: Programming Language :: Python :: 3
Classifier: Programming Language :: Python :: 3.7
Requires-Dist: ts3query
Requires-Dist: SQLAlchemy
Requires-Dist: SQLAlchemy-utils
Requires-Dist: ts3ekkoutil (>=0.0.20)
Requires-Dist: requests
Requires-Dist: python-mpv
Requires-Dist: youtube-dl
Requires-Dist: PyYAML
Provides-Extra: doc
Requires-Dist: sphinx ; extra == 'doc'
Requires-Dist: sphinx-autobuild ; extra == 'doc'
Requires-Dist: sphinx-rtd-theme ; extra == 'doc'
Provides-Extra: test
Requires-Dist: coverage ; extra == 'test'
Requires-Dist: alchemy-mock ; extra == 'test'
